sageintacctsdk/__init__.py
sageintacctsdk/exceptions.py
sageintacctsdk/sageintacctsdk.py
sageintacctsdk/apis/__init__.py
sageintacctsdk/apis/accounts.py
sageintacctsdk/apis/allocation_entry.py
sageintacctsdk/apis/allocations.py
sageintacctsdk/apis/ap_payments.py
sageintacctsdk/apis/api_base.py
sageintacctsdk/apis/ar_aging.py
sageintacctsdk/apis/ar_invoice_items.py
sageintacctsdk/apis/ar_invoices.py
sageintacctsdk/apis/ar_payments.py
sageintacctsdk/apis/attachments.py
sageintacctsdk/apis/bills.py
sageintacctsdk/apis/charge_card_accounts.py
sageintacctsdk/apis/charge_card_transactions.py
sageintacctsdk/apis/checking_accounts.py
sageintacctsdk/apis/classes.py
sageintacctsdk/apis/constants.py
sageintacctsdk/apis/contacts.py
sageintacctsdk/apis/contract_lines.py
sageintacctsdk/apis/contracts.py
sageintacctsdk/apis/cost_types.py
sageintacctsdk/apis/customers.py
sageintacctsdk/apis/departments.py
sageintacctsdk/apis/dimension_values.py
sageintacctsdk/apis/dimensions.py
sageintacctsdk/apis/employees.py
sageintacctsdk/apis/expense_payment_types.py
sageintacctsdk/apis/expense_reports.py
sageintacctsdk/apis/expense_types.py
sageintacctsdk/apis/gl_detail.py
sageintacctsdk/apis/inventory_control_price_list_entries.py
sageintacctsdk/apis/items.py
sageintacctsdk/apis/journal_entries.py
sageintacctsdk/apis/location_entities.py
sageintacctsdk/apis/locations.py
sageintacctsdk/apis/order_entry_transactions.py
sageintacctsdk/apis/projects.py
sageintacctsdk/apis/reimbursements.py
sageintacctsdk/apis/revenue_recognition_schedule_entries.py
sageintacctsdk/apis/revenue_recognition_schedules.py
sageintacctsdk/apis/savings_accounts.py
sageintacctsdk/apis/tasks.py
sageintacctsdk/apis/tax_details.py
sageintacctsdk/apis/vendors.py
sageintacctsdk-1.27.4.dist-info/licenses/LICENSE
sageintacctsdk-1.27.4.dist-info/METADATA
sageintacctsdk-1.27.4.dist-info/WHEEL
sageintacctsdk-1.27.4.dist-info/top_level.txt
sageintacctsdk-1.27.4.dist-info/RECORD
